airflow/providers/google/__init__.py
airflow/providers/google/get_provider_info.py
airflow/providers/google/go_module_utils.py
airflow/providers/google/version_compat.py
airflow/providers/google/3rd-party-licenses/LICENSES.txt
airflow/providers/google/3rd-party-licenses/NOTICE
airflow/providers/google/_vendor/__init__.py
airflow/providers/google/_vendor/json_merge_patch.py
airflow/providers/google/ads/.gitignore
airflow/providers/google/ads/__init__.py
airflow/providers/google/ads/hooks/__init__.py
airflow/providers/google/ads/hooks/ads.py
airflow/providers/google/ads/operators/__init__.py
airflow/providers/google/ads/operators/ads.py
airflow/providers/google/ads/transfers/__init__.py
airflow/providers/google/ads/transfers/ads_to_gcs.py
airflow/providers/google/assets/__init__.py
airflow/providers/google/assets/bigquery.py
airflow/providers/google/assets/gcs.py
airflow/providers/google/cloud/__init__.py
airflow/providers/google/cloud/_internal_client/__init__.py
airflow/providers/google/cloud/_internal_client/secret_manager_client.py
airflow/providers/google/cloud/bundles/__init__.py
airflow/providers/google/cloud/bundles/gcs.py
airflow/providers/google/cloud/fs/__init__.py
airflow/providers/google/cloud/fs/gcs.py
airflow/providers/google/cloud/hooks/__init__.py
airflow/providers/google/cloud/hooks/alloy_db.py
airflow/providers/google/cloud/hooks/bigquery.py
airflow/providers/google/cloud/hooks/bigquery_dts.py
airflow/providers/google/cloud/hooks/bigtable.py
airflow/providers/google/cloud/hooks/cloud_batch.py
airflow/providers/google/cloud/hooks/cloud_build.py
airflow/providers/google/cloud/hooks/cloud_composer.py
airflow/providers/google/cloud/hooks/cloud_logging.py
airflow/providers/google/cloud/hooks/cloud_memorystore.py
airflow/providers/google/cloud/hooks/cloud_run.py
airflow/providers/google/cloud/hooks/cloud_sql.py
airflow/providers/google/cloud/hooks/cloud_storage_transfer_service.py
airflow/providers/google/cloud/hooks/compute.py
apache_airflow_providers_google-19.2.0.dist-info/entry_points.txt
apache_airflow_providers_google-19.2.0.dist-info/licenses/LICENSE
apache_airflow_providers_google-19.2.0.dist-info/licenses/NOTICE
apache_airflow_providers_google-19.2.0.dist-info/WHEEL
apache_airflow_providers_google-19.2.0.dist-info/METADATA
apache_airflow_providers_google-19.2.0.dist-info/RECORD
