Metadata-Version: 2.4
Name: apache-airflow-providers-google
Version: 19.2.0
Summary: Provider package apache-airflow-providers-google for Apache Airflow
Keywords: airflow-provider,google,airflow,integration
Author-email: Apache Software Foundation <dev@airflow.apache.org>
Maintainer-email: Apache Software Foundation <dev@airflow.apache.org>
Requires-Python: >=3.10
License-Expression: Apache-2.0
Classifier: Development Status :: 5 - Production/Stable
Classifier: Environment :: Console
Classifier: Environment :: Web Environment
Classifier: Intended Audience :: Developers
Classifier: Intended Audience :: System Administrators
Classifier: Framework :: Apache Airflow
Classifier: Framework :: Apache Airflow :: Provider
Classifier: Programming Language :: Python :: 3.10
Classifier: Programming Language :: Python :: 3.11
Classifier: Programming Language :: Python :: 3.12
Classifier: Programming Language :: Python :: 3.13
Classifier: Topic :: System :: Monitoring
License-File: LICENSE
License-File: NOTICE
Requires-Dist: apache-airflow>=2.11.0
Requires-Dist: apache-airflow-providers-common-compat>=1.10.1
Requires-Dist: apache-airflow-providers-common-sql>=1.27.0
Requires-Dist: asgiref>=3.5.2
Requires-Dist: dill>=0.2.3
Requires-Dist: gcloud-aio-auth>=5.2.0
Requires-Dist: gcloud-aio-bigquery>=6.1.2
Requires-Dist: gcloud-aio-storage>=9.0.0
Requires-Dist: gcsfs>=2023.10.0
Requires-Dist: google-ads>=26.0.0,!=28.0.0.post2
Requires-Dist: google-analytics-admin>=0.9.0
Requires-Dist: google-api-core>=2.11.0,!=2.16.0,!=2.18.0
Requires-Dist: google-api-python-client>=2.0.2
Requires-Dist: google-auth>=2.29.0
Requires-Dist: google-auth-httplib2>=0.0.1
Requires-Dist: google-cloud-aiplatform[evaluation]>=1.98.0
Requires-Dist: ray[default]>=2.42.0 ; python_version < '3.13'
Requires-Dist: google-cloud-bigquery-storage>=2.31.0 ; python_version < '3.13'
Requires-Dist: google-cloud-alloydb>=0.4.0
Requires-Dist: google-cloud-automl>=2.12.0
Requires-Dist: google-cloud-bigquery>=3.24.0
Requires-Dist: google-cloud-bigquery-datatransfer>=3.13.0
Requires-Dist: google-cloud-bigtable>=2.17.0
Requires-Dist: google-cloud-build>=3.31.0
Requires-Dist: google-cloud-compute>=1.10.0
Requires-Dist: google-cloud-container>=2.52.0
Requires-Dist: google-cloud-datacatalog>=3.23.0
Requires-Dist: google-cloud-dataflow-client>=0.8.6
Requires-Dist: google-cloud-dataform>=0.5.0
Requires-Dist: google-cloud-dataplex>=2.6.0
Requires-Dist: google-cloud-dataproc>=5.21.0
Requires-Dist: google-cloud-dataproc-metastore>=1.12.0
Requires-Dist: google-cloud-dlp>=3.12.0
Requires-Dist: google-cloud-kms>=2.15.0
Requires-Dist: google-cloud-language>=2.9.0
Requires-Dist: google-cloud-logging>=3.5.0
Requires-Dist: google-cloud-managedkafka>=0.1.6
Requires-Dist: google-cloud-memcache>=1.7.0
Requires-Dist: google-cloud-monitoring>=2.18.0
Requires-Dist: google-cloud-orchestration-airflow>=1.10.0
Requires-Dist: google-cloud-os-login>=2.9.1
Requires-Dist: google-cloud-pubsub>=2.24.0
Requires-Dist: google-cloud-redis>=2.12.0
Requires-Dist: google-cloud-secret-manager>=2.16.0
Requires-Dist: google-cloud-spanner>=3.50.0
Requires-Dist: google-cloud-speech>=2.18.0
Requires-Dist: google-cloud-storage>=2.9.0
Requires-Dist: google-cloud-storage-transfer>=1.13.0
Requires-Dist: google-cloud-tasks>=2.13.0
Requires-Dist: google-cloud-texttospeech>=2.14.1
Requires-Dist: google-cloud-translate>=3.16.0
Requires-Dist: google-cloud-videointelligence>=2.11.0
Requires-Dist: google-cloud-vision>=3.4.0
Requires-Dist: google-cloud-workflows>=1.10.0
Requires-Dist: google-cloud-run>=0.10.0
Requires-Dist: google-cloud-batch>=0.13.0
Requires-Dist: grpcio-gcp>=0.2.2
Requires-Dist: httpx>=0.25.0
Requires-Dist: looker-sdk>=22.4.0,!=24.18.0
Requires-Dist: pandas-gbq>=0.7.0
Requires-Dist: pandas>=2.1.2; python_version <"3.13"
Requires-Dist: pandas>=2.2.3; python_version >="3.13"
Requires-Dist: proto-plus>=1.26.0
Requires-Dist: pyarrow>=16.1.0; python_version < '3.13'
Requires-Dist: pyarrow>=18.0.0; python_version >= '3.13'
Requires-Dist: python-slugify>=7.0.0
Requires-Dist: PyOpenSSL>=23.0.0
Requires-Dist: sqlalchemy-bigquery>=1.2.1
Requires-Dist: sqlalchemy-spanner>=1.6.2
Requires-Dist: tenacity>=8.3.0
Requires-Dist: immutabledict>=4.2.0
Requires-Dist: types-protobuf!=5.29.1.20250402,>=5.27.0
Requires-Dist: apache-airflow-providers-amazon>=2.6.0 ; extra == "amazon"
Requires-Dist: apache-beam[gcp]>=2.53.0 ; extra == "apache-beam" and ( python_version < "3.12")
Requires-Dist: apache-beam[gcp]>=2.57.0 ; extra == "apache-beam" and ( python_version >= "3.12" and python_version < "3.13")
Requires-Dist: apache-airflow-providers-apache-cassandra ; extra == "apache-cassandra"
Requires-Dist: apache-airflow-providers-cncf-kubernetes>=10.1.0 ; extra == "cncf-kubernetes"
Requires-Dist: apache-airflow-providers-fab>=2.0.0 ; extra == "fab" and ( python_version < '3.13')
Requires-Dist: apache-airflow-providers-facebook>=2.2.0 ; extra == "facebook"
Requires-Dist: apache-airflow-providers-http ; extra == "http"
Requires-Dist: plyvel>=1.5.1 ; extra == "leveldb" and ( python_version < '3.13')
Requires-Dist: apache-airflow-providers-microsoft-azure ; extra == "microsoft-azure"
Requires-Dist: apache-airflow-providers-microsoft-mssql ; extra == "microsoft-mssql"
Requires-Dist: apache-airflow-providers-mysql ; extra == "mysql"
Requires-Dist: apache-airflow-providers-openlineage ; extra == "openlineage"
Requires-Dist: apache-airflow-providers-oracle>=3.1.0 ; extra == "oracle"
Requires-Dist: apache-airflow-providers-postgres ; extra == "postgres"
Requires-Dist: apache-airflow-providers-presto ; extra == "presto"
Requires-Dist: apache-airflow-providers-salesforce ; extra == "salesforce"
Requires-Dist: apache-airflow-providers-sftp ; extra == "sftp"
Requires-Dist: apache-airflow-providers-ssh ; extra == "ssh"
Requires-Dist: apache-airflow-providers-standard ; extra == "standard"
Requires-Dist: apache-airflow-providers-trino ; extra == "trino"
Project-URL: Bug Tracker, https://github.com/apache/airflow/issues
Project-URL: Changelog, https://airflow.apache.org/docs/apache-airflow-providers-google/19.2.0/changelog.html
Project-URL: Documentation, https://airflow.apache.org/docs/apache-airflow-providers-google/19.2.0
Project-URL: Mastodon, https://fosstodon.org/@airflow
Project-URL: Slack Chat, https://s.apache.org/airflow-slack
Project-URL: Source Code, https://github.com/apache/airflow
Project-URL: YouTube, https://www.youtube.com/channel/UCSXwxpWZQ7XZ1WL3wqevChA/
Provides-Extra: amazon
Provides-Extra: apache-beam
Provides-Extra: apache-cassandra
Provides-Extra: cncf-kubernetes
Provides-Extra: fab
Provides-Extra: facebook
Provides-Extra: http
Provides-Extra: leveldb
Provides-Extra: microsoft-azure
Provides-Extra: microsoft-mssql
Provides-Extra: mysql
Provides-Extra: openlineage
Provides-Extra: oracle
Provides-Extra: postgres
Provides-Extra: presto
Provides-Extra: salesforce
Provides-Extra: sftp
Provides-Extra: ssh
Provides-Extra: standard
Provides-Extra: trino
